sorting_package_ruben/__init__.py
sorting_package_ruben/bubble_sort.py
sorting_package_ruben/insertion_sort.py
sorting_package_ruben/quick_sort.py
sorting_package_ruben/selection_sort.py
sorting_package_ruben-0.5.dist-info/METADATA
sorting_package_ruben-0.5.dist-info/WHEEL
sorting_package_ruben-0.5.dist-info/top_level.txt
sorting_package_ruben-0.5.dist-info/RECORD
