Metadata-Version: 2.1
Name: sorting-package-ruben
Version: 0.5
Summary: sorting Algorithms to be uploaded in Pypi
Home-page: http://github.com/sorting_packsge_ruben
Author: Ruben Villalon
Author-email: ruben@example.com
License: MIT
Platform: UNKNOWN
